odoo/addons/product_get_price_helper/README.rst
odoo/addons/product_get_price_helper/__init__.py
odoo/addons/product_get_price_helper/__manifest__.py
odoo/addons/product_get_price_helper/utils.py
odoo/addons/product_get_price_helper/demo/account.xml
odoo/addons/product_get_price_helper/demo/pricelist.xml
odoo/addons/product_get_price_helper/i18n/it.po
odoo/addons/product_get_price_helper/i18n/product_get_price_helper.pot
odoo/addons/product_get_price_helper/models/__init__.py
odoo/addons/product_get_price_helper/models/product_product.py
odoo/addons/product_get_price_helper/readme/CONTRIBUTORS.md
odoo/addons/product_get_price_helper/readme/DESCRIPTION.md
odoo/addons/product_get_price_helper/static/description/icon.png
odoo/addons/product_get_price_helper/static/description/index.html
odoo/addons/product_get_price_helper/tests/__init__.py
odoo/addons/product_get_price_helper/tests/test_product.py
odoo_addon_product_get_price_helper-18.0.1.1.0.dist-info/METADATA
odoo_addon_product_get_price_helper-18.0.1.1.0.dist-info/WHEEL
odoo_addon_product_get_price_helper-18.0.1.1.0.dist-info/top_level.txt
odoo_addon_product_get_price_helper-18.0.1.1.0.dist-info/RECORD
